{"title":"Hello World  love me  gc","uid":"3ff55b7e65239c9493d6e11c6b8aeecd","slug":"hello-world","date":"2022-11-10T12:19:15.586Z","updated":"2022-11-10T12:19:15.586Z","comments":true,"path":"api/articles/hello-world.json","keywords":null,"cover":null,"content":"<h2 id=\"edit-from-github\"><a href=\"#edit-from-github\" class=\"headerlink\" title=\"edit from github\"></a>edit from github</h2><p>hello </p>\n<p>*welcome to my blog</p>\n<p>*今天是2022年11月10号我开始写我博客的第一篇文章</p>\n<p>*以后我会在这个博客里记录我的学习历程</p>\n<p>O(∩_∩)O</p>\n<p>More info: <a href=\"https://hexo.io/docs/one-command-deployment.html\">Deployment</a></p>\n","text":"edit from githubhello *welcome to my blog *今天是2022年11月10号我开始写我博客的第一篇文章 *以后我会在这个博客里记录我的学习历程 O(∩_∩)O More info: Deployment ","link":"","photos":[],"count_time":{"symbolsCount":122,"symbolsTime":"1 mins."},"categories":[],"tags":[],"toc":"<ol class=\"toc\"><li class=\"toc-item toc-level-2\"><a class=\"toc-link\" href=\"#edit-from-github\"><span class=\"toc-text\">edit from github</span></a></li></ol>","author":{"name":"gcvsworld","slug":"blog-author","avatar":"https://img-blog.csdnimg.cn/20210313122054101.png","link":"/","description":"一个正在努力学习前端知识的年轻人<br /> 我的github：<b>https://github.com/gcvsworld</b>","socials":{"github":"","twitter":"","stackoverflow":"","wechat":"","qq":"","weibo":"","zhihu":"","csdn":"","juejin":"","customs":{}}},"mapped":true,"prev_post":{},"next_post":{}}